pycram/__init__.py
pycram/pycram.py
pycram-0.0.2.dist-info/METADATA
pycram-0.0.2.dist-info/WHEEL
pycram-0.0.2.dist-info/licenses/LICENSE
pycram-0.0.2.dist-info/RECORD
