Metadata-Version: 2.1
Name: pycram
Version: 0.0.2
Summary: A python module to provide methods and basic functionality for flash cards.
Project-URL: Homepage, https://github.com/TylerPantuso
Author-email: Tyler Pantuso <tylerpantuso@gmail.com>
License-File: LICENSE
Classifier: License :: OSI Approved :: MIT License
Classifier: Operating System :: OS Independent
Classifier: Programming Language :: Python :: 3
Requires-Python: >3.10
